exo/DecisionTree_Model.joblib
exo/LogisticRegression_Model.joblib
exo/NaiveBayes_Model.joblib
exo/NeuralNetwork_Model.joblib
exo/__init__.py
exo/exocore.py
exopassword-0.0.8.dist-info/LICENSE
exopassword-0.0.8.dist-info/METADATA
exopassword-0.0.8.dist-info/WHEEL
exopassword-0.0.8.dist-info/top_level.txt
exopassword-0.0.8.dist-info/RECORD
