Metadata-Version: 2.1
Name: exopassword
Version: 0.0.8
Summary: ExoPassword is a Password Strength Analyzing module that combines Machine Learning, rule-based scoring, and breach detection to provide detailed insight regarding your passwords.
Home-page: https://github.com/owaspvit/exo
Author: Apratim Shukla, Mayank Tolani
Author-email: apratimshukla6@gmail.com
License: MIT
Download-URL: https://pypi.org/project/exopassword/
Keywords: Exo,ExoPassword,PasswordAnalysis
Platform: UNKNOWN
License-File: LICENSE
Requires-Dist: requests
Requires-Dist: joblib
Requires-Dist: scikit-learn (==0.24.1)
